{
	"name": "pl_incremental_load",
	"properties": {
		"activities": [
			{
				"name": "LkpOldWatermark",
				"type": "Lookup",
				"dependsOn": [],
				"policy": {
					"timeout": "0.12:00:00",
					"retry": 0,
					"retryIntervalInSeconds": 30,
					"secureOutput": false,
					"secureInput": false
				},
				"userProperties": [],
				"typeProperties": {
					"source": {
						"type": "AzureSqlSource",
						"queryTimeout": "02:00:00",
						"partitionOption": "None"
					},
					"dataset": {
						"referenceName": "watermarkDataset",
						"type": "DatasetReference"
					}
				}
			},
			{
				"name": "LkpNewWatermark",
				"type": "Lookup",
				"dependsOn": [],
				"policy": {
					"timeout": "0.12:00:00",
					"retry": 0,
					"retryIntervalInSeconds": 30,
					"secureOutput": false,
					"secureInput": false
				},
				"userProperties": [],
				"typeProperties": {
					"source": {
						"type": "AzureSqlSource",
						"sqlReaderQuery": "select max(LastModifytime) AS LatestDate from dbo.data_source\n",
						"queryTimeout": "02:00:00",
						"partitionOption": "None"
					},
					"dataset": {
						"referenceName": "SourceDataset",
						"type": "DatasetReference"
					}
				}
			},
			{
				"name": "Copy data",
				"type": "Copy",
				"dependsOn": [
					{
						"activity": "LkpNewWatermark",
						"dependencyConditions": [
							"Succeeded"
						]
					},
					{
						"activity": "LkpOldWatermark",
						"dependencyConditions": [
							"Succeeded"
						]
					}
				],
				"policy": {
					"timeout": "0.12:00:00",
					"retry": 0,
					"retryIntervalInSeconds": 30,
					"secureOutput": false,
					"secureInput": false
				},
				"userProperties": [],
				"typeProperties": {
					"source": {
						"type": "AzureSqlSource",
						"sqlReaderQuery": {
							"value": "SELECT *\nFROM dbo.Data_source\nWHERE LastModifytime >  '@{activity('LkpOldWatermark').output.firstRow.WatermarkValue}'\n  AND LastModifytime <= '@{activity('LkpNewWatermark').output.firstRow.LatestDate}'\n",
							"type": "Expression"
						},
						"queryTimeout": "02:00:00",
						"partitionOption": "None"
					},
					"sink": {
						"type": "DelimitedTextSink",
						"storeSettings": {
							"type": "AzureBlobFSWriteSettings"
						},
						"formatSettings": {
							"type": "DelimitedTextWriteSettings",
							"quoteAllText": true,
							"fileExtension": ".txt"
						}
					},
					"enableStaging": false,
					"translator": {
						"type": "TabularTranslator",
						"typeConversion": true,
						"typeConversionSettings": {
							"allowDataTruncation": true,
							"treatBooleanAsNumber": false
						}
					}
				},
				"inputs": [
					{
						"referenceName": "SourceDataset",
						"type": "DatasetReference"
					}
				],
				"outputs": [
					{
						"referenceName": "DelimitedText14",
						"type": "DatasetReference"
					}
				]
			},
			{
				"name": "Update_Watermark_to_latestdate",
				"type": "SqlServerStoredProcedure",
				"dependsOn": [
					{
						"activity": "Copy data",
						"dependencyConditions": [
							"Succeeded"
						]
					}
				],
				"policy": {
					"timeout": "0.12:00:00",
					"retry": 0,
					"retryIntervalInSeconds": 30,
					"secureOutput": false,
					"secureInput": false
				},
				"userProperties": [],
				"typeProperties": {
					"storedProcedureName": "[dbo].[update_watermark]",
					"storedProcedureParameters": {
						"LastModifiedtime": {
							"value": {
								"value": "@activity('LkpNewWatermark').output.firstRow.LatestDate",
								"type": "Expression"
							},
							"type": "DateTime"
						},
						"TableName": {
							"value": {
								"value": "@activity('LkpOldWatermark').output.firstRow.Tablename",
								"type": "Expression"
							},
							"type": "String"
						}
					}
				},
				"linkedServiceName": {
					"referenceName": "lnk_azuresql",
					"type": "LinkedServiceReference"
				}
			}
		],
		"annotations": []
	}
}